{
  "framerate": "24",
  "images": [
    "spriteSheets/sheet_player_walk-ultra.png"
  ],
  "frames": [
    [
      3448,
      0,
      171,
      278,
      0,
      96,
      49
    ],
    [
      1377,
      278,
      172,
      279,
      0,
      93,
      50
    ],
    [
      2412,
      278,
      173,
      280,
      0,
      90,
      50
    ],
    [
      2760,
      278,
      175,
      280,
      0,
      89,
      50
    ],
    [
      1722,
      278,
      173,
      279,
      0,
      90,
      52
    ],
    [
      172,
      278,
      172,
      278,
      0,
      92,
      53
    ],
    [
      2243,
      0,
      171,
      277,
      0,
      94,
      54
    ],
    [
      2414,
      0,
      172,
      277,
      0,
      95,
      56
    ],
    [
      2586,
      0,
      172,
      277,
      0,
      95,
      57
    ],
    [
      3792,
      278,
      171,
      282,
      0,
      95,
      59
    ],
    [
      1895,
      278,
      172,
      280,
      0,
      96,
      55
    ],
    [
      1033,
      278,
      172,
      279,
      0,
      96,
      52
    ],
    [
      3275,
      0,
      173,
      277,
      0,
      97,
      49
    ],
    [
      0,
      278,
      172,
      278,
      0,
      93,
      49
    ],
    [
      517,
      278,
      173,
      278,
      0,
      90,
      49
    ],
    [
      1897,
      0,
      175,
      276,
      0,
      89,
      48
    ],
    [
      1724,
      0,
      173,
      276,
      0,
      90,
      49
    ],
    [
      1210,
      0,
      171,
      275,
      0,
      91,
      50
    ],
    [
      1381,
      0,
      171,
      275,
      0,
      94,
      51
    ],
    [
      1039,
      0,
      171,
      274,
      0,
      94,
      52
    ],
    [
      1552,
      0,
      172,
      275,
      0,
      95,
      53
    ],
    [
      690,
      278,
      171,
      279,
      0,
      95,
      54
    ],
    [
      3106,
      278,
      171,
      281,
      0,
      95,
      52
    ],
    [
      3277,
      278,
      172,
      281,
      0,
      96,
      51
    ],
    [
      3448,
      0,
      171,
      278,
      0,
      96,
      49
    ],
    [
      861,
      278,
      172,
      279,
      0,
      93,
      50
    ],
    [
      2239,
      278,
      173,
      280,
      0,
      90,
      50
    ],
    [
      2585,
      278,
      175,
      280,
      0,
      89,
      50
    ],
    [
      1549,
      278,
      173,
      279,
      0,
      90,
      52
    ],
    [
      3791,
      0,
      172,
      278,
      0,
      92,
      53
    ],
    [
      2072,
      0,
      171,
      277,
      0,
      94,
      54
    ],
    [
      2930,
      0,
      172,
      277,
      0,
      95,
      56
    ],
    [
      2758,
      0,
      172,
      277,
      0,
      95,
      57
    ],
    [
      3621,
      278,
      171,
      282,
      0,
      95,
      59
    ],
    [
      2067,
      278,
      172,
      280,
      0,
      96,
      55
    ],
    [
      1205,
      278,
      172,
      279,
      0,
      96,
      52
    ],
    [
      3102,
      0,
      173,
      277,
      0,
      97,
      49
    ],
    [
      3619,
      0,
      172,
      278,
      0,
      93,
      49
    ],
    [
      344,
      278,
      173,
      278,
      0,
      90,
      49
    ],
    [
      1897,
      0,
      175,
      276,
      0,
      89,
      48
    ],
    [
      1724,
      0,
      173,
      276,
      0,
      90,
      49
    ],
    [
      1210,
      0,
      171,
      275,
      0,
      91,
      50
    ],
    [
      1381,
      0,
      171,
      275,
      0,
      94,
      51
    ],
    [
      1039,
      0,
      171,
      274,
      0,
      94,
      52
    ],
    [
      1552,
      0,
      172,
      275,
      0,
      95,
      53
    ],
    [
      690,
      278,
      171,
      279,
      0,
      95,
      54
    ],
    [
      2935,
      278,
      171,
      281,
      0,
      95,
      52
    ],
    [
      3449,
      278,
      172,
      281,
      0,
      96,
      51
    ]
  ],
  "animations": {
    "Player_rig_WALK": [
      0,
      47
    ]
  }
}